basic_data_science/__init__.py
basic_data_science/readcsv.py
Basic_Data_Science-1.0.dist-info/LICENSE.LIC
Basic_Data_Science-1.0.dist-info/METADATA
Basic_Data_Science-1.0.dist-info/WHEEL
Basic_Data_Science-1.0.dist-info/top_level.txt
Basic_Data_Science-1.0.dist-info/RECORD
